{
    "cordova-plugin-whitelist": {
        "source": {
            "type": "registry",
            "id": "cordova-plugin-whitelist@1"
        },
        "is_top_level": true,
        "variables": {}
    },
    "cordova-plugin-geolocation": {
        "source": {
            "type": "git",
            "url": "https://github.com/apache/cordova-plugin-geolocation.git",
            "subdir": "."
        },
        "is_top_level": true,
        "variables": {}
    },
    "cordova-plugin-compat": {
        "source": {
            "type": "registry",
            "id": "cordova-plugin-compat"
        },
        "is_top_level": false,
        "variables": {}
    },
    "cordova-plugin-googlemaps": {
        "source": {
            "type": "registry",
            "id": "cordova-plugin-googlemaps"
        },
        "is_top_level": true,
        "variables": {
            "API_KEY_FOR_ANDROID": "AIzaSyBX7lQwfUQL7RvrinBmEhSZpKlYUzFKZLs",
            "API_KEY_FOR_IOS": "AIzaSyDKvaZN_e3dej1b_2bbWP65FtTGCnhl1fQ"
        }
    },
    "de.appplant.cordova.plugin.local-notification": {
        "source": {
            "type": "git",
            "url": "https://github.com/katzer/cordova-plugin-local-notifications",
            "subdir": "."
        },
        "is_top_level": true,
        "variables": {}
    },
    "cordova-plugin-device": {
        "source": {
            "type": "registry",
            "id": "cordova-plugin-device"
        },
        "is_top_level": false,
        "variables": {}
    },
    "cordova-plugin-app-event": {
        "source": {
            "type": "registry",
            "id": "cordova-plugin-app-event"
        },
        "is_top_level": false,
        "variables": {}
    }
}